chirimbolito/Chirimbolito.py
chirimbolito/ChirimbolitoDisplay.py
chirimbolito/ChirimbolitoInfo.py
chirimbolito/__init__.py
chirimbolito-4.dist-info/DESCRIPTION.rst
chirimbolito-4.dist-info/METADATA
chirimbolito-4.dist-info/RECORD
chirimbolito-4.dist-info/WHEEL
chirimbolito-4.dist-info/entry_points.txt
chirimbolito-4.dist-info/metadata.json
chirimbolito-4.dist-info/top_level.txt
