Metadata-Version: 2.0
Name: chirimbolito
Version: 4
Summary: A Bitcoin address monitoring tool built with a Raspberry Pi and a LCD display
Home-page: https://github.com/facastagnini/python-chirimbolito
Author: Federico Ariel Castagnini
Author-email: federico.castagnini@protonmail.com
License: UNKNOWN
Keywords: raspberry pi rpi bitcoin lcd wallet monitoring
Platform: UNKNOWN
Classifier: Development Status :: 4 - Beta
Classifier: Intended Audience :: Developers
Classifier: License :: OSI Approved :: GNU General Public License v3 (GPLv3)
Classifier: Programming Language :: Python :: 3
Classifier: Programming Language :: Python :: 3.4
Classifier: Programming Language :: Python :: 3.5
Classifier: Programming Language :: Python :: 3.6
Requires-Dist: RPi.GPIO
Requires-Dist: Adafruit-CharLCD
Requires-Dist: requests
Requires-Dist: ballpark
Requires-Dist: future
Requires-Dist: pandas
